{"created_at":"Fri Apr 10 17:03:48 +0000 2020","id":1248657949091704832,"id_str":"1248657949091704832","text":"FRIDAY: EDUCATION \u2014 advocate for quality education and schools \nFor more information, visit:\u2026 https:\/\/t.co\/DC2ETixxbW","display_text_range":[0,140],"source":"\u003ca href=\"https:\/\/mobile.twitter.com\" rel=\"nofollow\"\u003eTwitter Web App\u003c\/a\u003e","truncated":true,"in_reply_to_status_id":null,"in_reply_to_status_id_str":null,"in_reply_to_user_id":null,"in_reply_to_user_id_str":null,"in_reply_to_screen_name":null,"user":{"id":237024183,"id_str":"237024183","name":"Ventura County Public Health","screen_name":"vcpublichealth","location":"Ventura County","url":"http:\/\/vchca.org","description":"Caring for individuals, families and communities. https:\/\/www.facebook.com\/VCHCA","translator_type":"none","protected":false,"verified":false,"followers_count":593,"friends_count":112,"listed_count":23,"favourites_count":16,"statuses_count":145,"created_at":"Tue Jan 11 22:26:01 +0000 2011","utc_offset":null,"time_zone":null,"geo_enabled":true,"lang":null,"contributors_enabled":false,"is_translator":false,"profile_background_color":"C0DEED","profile_background_image_url":"http:\/\/abs.twimg.com\/images\/themes\/theme1\/bg.png","profile_background_image_url_https":"https:\/\/abs.twimg.com\/images\/themes\/theme1\/bg.png","profile_background_tile":false,"profile_link_color":"0084B4","profile_sidebar_border_color":"FFFFFF","profile_sidebar_fill_color":"DDEEF6","profile_text_color":"333333","profile_use_background_image":true,"profile_image_url":"http:\/\/pbs.twimg.com\/profile_images\/1146108444354605056\/fp7ZX6sL_normal.png","profile_image_url_https":"https:\/\/pbs.twimg.com\/profile_images\/1146108444354605056\/fp7ZX6sL_normal.png","profile_banner_url":"https:\/\/pbs.twimg.com\/profile_banners\/237024183\/1585176941","default_profile":false,"default_profile_image":false,"following":null,"follow_request_sent":null,"notifications":null},"geo":null,"coordinates":null,"place":null,"contributors":null,"is_quote_status":false,"extended_tweet":{"full_text":"FRIDAY: EDUCATION \u2014 advocate for quality education and schools \nFor more information, visit: https:\/\/t.co\/H3F1jgAVfI\n#APHA2020 #VCPublicHealth https:\/\/t.co\/ad4ilqBolW","display_text_range":[0,142],"entities":{"hashtags":[{"text":"APHA2020","indices":[117,126]},{"text":"VCPublicHealth","indices":[127,142]}],"urls":[{"url":"https:\/\/t.co\/H3F1jgAVfI","expanded_url":"http:\/\/bit.ly\/NPHWEducation","display_url":"bit.ly\/NPHWEducation","indices":[93,116]}],"user_mentions":[],"symbols":[],"media":[{"id":1248657942502453248,"id_str":"1248657942502453248","indices":[143,166],"media_url":"http:\/\/pbs.twimg.com\/media\/EVQfyHTUMAAbksZ.jpg","media_url_https":"https:\/\/pbs.twimg.com\/media\/EVQfyHTUMAAbksZ.jpg","url":"https:\/\/t.co\/ad4ilqBolW","display_url":"pic.twitter.com\/ad4ilqBolW","expanded_url":"https:\/\/twitter.com\/vcpublichealth\/status\/1248657949091704832\/photo\/1","type":"photo","sizes":{"small":{"w":680,"h":340,"resize":"fit"},"thumb":{"w":150,"h":150,"resize":"crop"},"medium":{"w":1024,"h":512,"resize":"fit"},"large":{"w":1024,"h":512,"resize":"fit"}}}]},"extended_entities":{"media":[{"id":1248657942502453248,"id_str":"1248657942502453248","indices":[143,166],"media_url":"http:\/\/pbs.twimg.com\/media\/EVQfyHTUMAAbksZ.jpg","media_url_https":"https:\/\/pbs.twimg.com\/media\/EVQfyHTUMAAbksZ.jpg","url":"https:\/\/t.co\/ad4ilqBolW","display_url":"pic.twitter.com\/ad4ilqBolW","expanded_url":"https:\/\/twitter.com\/vcpublichealth\/status\/1248657949091704832\/photo\/1","type":"photo","sizes":{"small":{"w":680,"h":340,"resize":"fit"},"thumb":{"w":150,"h":150,"resize":"crop"},"medium":{"w":1024,"h":512,"resize":"fit"},"large":{"w":1024,"h":512,"resize":"fit"}}}]}},"quote_count":0,"reply_count":0,"retweet_count":0,"favorite_count":0,"entities":{"hashtags":[],"urls":[{"url":"https:\/\/t.co\/DC2ETixxbW","expanded_url":"https:\/\/twitter.com\/i\/web\/status\/1248657949091704832","display_url":"twitter.com\/i\/web\/status\/1\u2026","indices":[94,117]}],"user_mentions":[],"symbols":[]},"favorited":false,"retweeted":false,"possibly_sensitive":false,"filter_level":"low","lang":"en","timestamp_ms":"1586538228663"}
