{"created_at":"Fri Apr 10 17:03:56 +0000 2020","id":1248657982658920453,"id_str":"1248657982658920453","text":"@arislvr you are sp*ming me enough https:\/\/t.co\/eTgINCUG9w","display_text_range":[9,58],"source":"\u003ca href=\"http:\/\/twitter.com\/download\/iphone\" rel=\"nofollow\"\u003eTwitter for iPhone\u003c\/a\u003e","truncated":false,"in_reply_to_status_id":1248656433622798336,"in_reply_to_status_id_str":"1248656433622798336","in_reply_to_user_id":1241295768323055616,"in_reply_to_user_id_str":"1241295768323055616","in_reply_to_screen_name":"arislvr","user":{"id":1118785803805777920,"id_str":"1118785803805777920","name":"polina\u2077 LOONA SNS FREEDOM","screen_name":"yejifilter","location":"lona itzy bts ; s\/h","url":null,"description":"are u yeji or not im NOT interested in non yeji people","translator_type":"none","protected":false,"verified":false,"followers_count":1020,"friends_count":868,"listed_count":24,"favourites_count":95109,"statuses_count":19041,"created_at":"Thu Apr 18 07:58:16 +0000 2019","utc_offset":null,"time_zone":null,"geo_enabled":false,"lang":null,"contributors_enabled":false,"is_translator":false,"profile_background_color":"F5F8FA","profile_background_image_url":"","profile_background_image_url_https":"","profile_background_tile":false,"profile_link_color":"1DA1F2","profile_sidebar_border_color":"C0DEED","profile_sidebar_fill_color":"DDEEF6","profile_text_color":"333333","profile_use_background_image":true,"profile_image_url":"http:\/\/pbs.twimg.com\/profile_images\/1248552173144666113\/S6G4gSVZ_normal.jpg","profile_image_url_https":"https:\/\/pbs.twimg.com\/profile_images\/1248552173144666113\/S6G4gSVZ_normal.jpg","profile_banner_url":"https:\/\/pbs.twimg.com\/profile_banners\/1118785803805777920\/1586513011","default_profile":true,"default_profile_image":false,"following":null,"follow_request_sent":null,"notifications":null},"geo":null,"coordinates":null,"place":null,"contributors":null,"is_quote_status":false,"quote_count":0,"reply_count":0,"retweet_count":0,"favorite_count":0,"entities":{"hashtags":[],"urls":[],"user_mentions":[{"screen_name":"arislvr","name":"miri\u2077","id":1241295768323055616,"id_str":"1241295768323055616","indices":[0,8]}],"symbols":[],"media":[{"id":1245321494252720128,"id_str":"1245321494252720128","indices":[35,58],"additional_media_info":{"monetizable":false},"media_url":"http:\/\/pbs.twimg.com\/ext_tw_video_thumb\/1245321494252720128\/pu\/img\/PygA_PlpCRvWv4XE.jpg","media_url_https":"https:\/\/pbs.twimg.com\/ext_tw_video_thumb\/1245321494252720128\/pu\/img\/PygA_PlpCRvWv4XE.jpg","url":"https:\/\/t.co\/eTgINCUG9w","display_url":"pic.twitter.com\/eTgINCUG9w","expanded_url":"https:\/\/twitter.com\/yeji_mp4\/status\/1245322428961734656\/video\/1","type":"photo","sizes":{"thumb":{"w":150,"h":150,"resize":"crop"},"small":{"w":680,"h":680,"resize":"fit"},"medium":{"w":720,"h":720,"resize":"fit"},"large":{"w":720,"h":720,"resize":"fit"}},"source_status_id":1245322428961734656,"source_status_id_str":"1245322428961734656","source_user_id":1239227643775651841,"source_user_id_str":"1239227643775651841"}]},"extended_entities":{"media":[{"id":1245321494252720128,"id_str":"1245321494252720128","indices":[35,58],"additional_media_info":{"monetizable":false},"media_url":"http:\/\/pbs.twimg.com\/ext_tw_video_thumb\/1245321494252720128\/pu\/img\/PygA_PlpCRvWv4XE.jpg","media_url_https":"https:\/\/pbs.twimg.com\/ext_tw_video_thumb\/1245321494252720128\/pu\/img\/PygA_PlpCRvWv4XE.jpg","url":"https:\/\/t.co\/eTgINCUG9w","display_url":"pic.twitter.com\/eTgINCUG9w","expanded_url":"https:\/\/twitter.com\/yeji_mp4\/status\/1245322428961734656\/video\/1","type":"video","video_info":{"aspect_ratio":[1,1],"duration_millis":79220,"variants":[{"content_type":"application\/x-mpegURL","url":"https:\/\/video.twimg.com\/ext_tw_video\/1245321494252720128\/pu\/pl\/xjNzsStqLwlHpO5X.m3u8?tag=10"},{"bitrate":1280000,"content_type":"video\/mp4","url":"https:\/\/video.twimg.com\/ext_tw_video\/1245321494252720128\/pu\/vid\/720x720\/DupX-oqxD9e1Fd3x.mp4?tag=10"},{"bitrate":432000,"content_type":"video\/mp4","url":"https:\/\/video.twimg.com\/ext_tw_video\/1245321494252720128\/pu\/vid\/320x320\/q1N5ykwgZlQ6kqXI.mp4?tag=10"},{"bitrate":832000,"content_type":"video\/mp4","url":"https:\/\/video.twimg.com\/ext_tw_video\/1245321494252720128\/pu\/vid\/480x480\/gn7Ht5IQ9J3ajNQw.mp4?tag=10"}]},"sizes":{"thumb":{"w":150,"h":150,"resize":"crop"},"small":{"w":680,"h":680,"resize":"fit"},"medium":{"w":720,"h":720,"resize":"fit"},"large":{"w":720,"h":720,"resize":"fit"}},"source_status_id":1245322428961734656,"source_status_id_str":"1245322428961734656","source_user_id":1239227643775651841,"source_user_id_str":"1239227643775651841"}]},"favorited":false,"retweeted":false,"possibly_sensitive":false,"filter_level":"low","lang":"en","timestamp_ms":"1586538236666"}
